csa_abcLR.py
csa_abcLR-1.0.2.dist-info/LICENSE.txt
csa_abcLR-1.0.2.dist-info/METADATA
csa_abcLR-1.0.2.dist-info/WHEEL
csa_abcLR-1.0.2.dist-info/top_level.txt
csa_abcLR-1.0.2.dist-info/RECORD
