Metadata-Version: 2.1
Name: csa-abcLR
Version: 1.0.2
Summary: CSA-ABC-LR is a classification method that combines The CSA and The ABC algorithm with a logistic regression classification model
Home-page: https://github.com/kagandedeturk/CSA-ABC-LR
Author: Bilge Kagan Dedeturk
Author-email: kagandedeturk@gmail.com
License: UNKNOWN
Platform: UNKNOWN
Classifier: Programming Language :: Python :: 3.7
Classifier: Programming Language :: Python :: 3.10
Classifier: License :: OSI Approved :: BSD License
Classifier: Operating System :: OS Independent
License-File: LICENSE.txt
